compress/__init__.py
compress/_version.py
compress/api.py
compress/impl.py
compress/paths.py
compress/docs/__init__.py
compress/tests/__init__.py
compress/tests/helper.py
compress/vendor/__init__.py
compress/vendor/better_enum.py
compress/vendor/pytest_cov_helper.py
compress/vendor/timer.py
compress-0.1.1.dist-info/AUTHORS.rst
compress-0.1.1.dist-info/LICENSE.txt
compress-0.1.1.dist-info/METADATA
compress-0.1.1.dist-info/WHEEL
compress-0.1.1.dist-info/top_level.txt
compress-0.1.1.dist-info/RECORD
